mocks/__init__.py
mocks/setup.py
mocks/openedx/__init__.py
mocks/openedx/core/__init__.py
mocks/openedx/core/djangoapps/__init__.py
mocks/openedx/core/djangoapps/plugins/__init__.py
mocks/openedx/core/djangoapps/plugins/constants.py
site_config_client/__init__.py
site_config_client/admin.py
site_config_client/apps.py
site_config_client/client.py
site_config_client/django_cache.py
site_config_client/exceptions.py
site_config_client/google_cloud_storage.py
site_config_client/models.py
site_config_client/migrations/0001_initial.py
site_config_client/migrations/__init__.py
site_config_client/openedx/__init__.py
site_config_client/openedx/adapter.py
site_config_client/openedx/api.py
site_config_client/openedx/features.py
site_config_client/openedx/test_helpers.py
site_config_client/openedx/settings/__init__.py
site_config_client/openedx/settings/production.py
site_config_client/openedx/settings/test.py
tests/__init__.py
tests/test_adapter.py
tests/test_admin.py
tests/test_apps.py
tests/test_client.py
tests/test_django_cache.py
tests/test_features.py
tests/test_google_cloud_storage.py
tests/test_openedx_api.py
tests/test_openedx_test_helpers.py
tests/test_plugin_settings.py
site_configuration_client-0.2.4.dist-info/LICENSE
site_configuration_client-0.2.4.dist-info/METADATA
site_configuration_client-0.2.4.dist-info/WHEEL
site_configuration_client-0.2.4.dist-info/entry_points.txt
site_configuration_client-0.2.4.dist-info/top_level.txt
site_configuration_client-0.2.4.dist-info/RECORD
