Metadata-Version: 2.1
Name: site-configuration-client
Version: 0.2.4
Summary: Python client library for Site Configuration API
Home-page: https://github.com/appsembler/site-configuration-client
Classifier: Intended Audience :: Developers
Classifier: Operating System :: OS Independent
Classifier: Programming Language :: Python :: 3.9
License-File: LICENSE
Requires-Dist: requests (>=2.20.0)
